duckplus/__init__.py
duckplus/_table_utils.py
duckplus/duckcon.py
duckplus/extensions.py
duckplus/relation.py
duckplus/schema.py
duckplus/table.py
duckplus/examples/__init__.py
duckplus/examples/pi_demo.py
duckplus/examples/sales_pipeline.py
duckplus/examples/traceability_pipeline.py
duckplus/functions/__init__.py
duckplus/functions/_base.py
duckplus/functions/aggregate/__init__.py
duckplus/functions/aggregate/approximation.py
duckplus/functions/aggregate/arg_extrema.py
duckplus/functions/aggregate/averages.py
duckplus/functions/aggregate/bitstring.py
duckplus/functions/aggregate/bitwise.py
duckplus/functions/aggregate/boolean.py
duckplus/functions/aggregate/counting.py
duckplus/functions/aggregate/extrema.py
duckplus/functions/aggregate/extremum_by_value.py
duckplus/functions/aggregate/generic.py
duckplus/functions/aggregate/list.py
duckplus/functions/aggregate/map.py
duckplus/functions/aggregate/median.py
duckplus/functions/aggregate/mode.py
duckplus/functions/aggregate/ordering.py
duckplus/functions/aggregate/quantiles.py
duckplus/functions/aggregate/regression.py
duckplus/functions/aggregate/statistics.py
duckplus/functions/aggregate/string.py
duckplus/functions/aggregate/summation.py
duckplus/functions/scalar/__init__.py
duckplus/functions/scalar/list.py
duckplus/functions/scalar/postgres_privilege.py
duckplus/functions/scalar/postgres_visibility.py
duckplus/functions/scalar/string.py
duckplus/functions/scalar/system.py
duckplus/io/__init__.py
duckplus/static_typed/__init__.py
duckplus/static_typed/_generated_function_namespaces.py
duckplus/static_typed/_generated_function_namespaces.pyi
duckplus/static_typed/dependencies.py
duckplus/static_typed/ducktype.py
duckplus/static_typed/ducktype.pyi
duckplus/static_typed/expression.py
duckplus/static_typed/functions.py
duckplus/static_typed/select.py
duckplus/static_typed/expressions/__init__.py
duckplus/static_typed/expressions/base.py
duckplus/static_typed/expressions/binary.py
duckplus-1.4.7.dist-info/METADATA
duckplus-1.4.7.dist-info/WHEEL
duckplus-1.4.7.dist-info/top_level.txt
duckplus-1.4.7.dist-info/RECORD
